getDataDeps.py
getDataDeps-0.0.22.dist-info/LICENSE
getDataDeps-0.0.22.dist-info/METADATA
getDataDeps-0.0.22.dist-info/WHEEL
getDataDeps-0.0.22.dist-info/entry_points.txt
getDataDeps-0.0.22.dist-info/top_level.txt
getDataDeps-0.0.22.dist-info/RECORD
