Metadata-Version: 2.1
Name: getDataDeps
Version: 0.0.22
Summary: A CLI to map the flow of data in your project
Home-page: https://github.com/lmgibson/getDataDeps
Author: Landon Gibson
Author-email: landon.g42@gmail.com
License: UNKNOWN
Project-URL: Source, https://github.com/lmgibson/getDataDeps
Platform: UNKNOWN
Classifier: Development Status :: 4 - Beta
Classifier: Programming Language :: Python :: 3
Classifier: License :: OSI Approved :: MIT License
Classifier: Operating System :: OS Independent
Classifier: Programming Language :: Python :: 3.6
Classifier: Programming Language :: Python :: 3.7
Classifier: Programming Language :: Python :: 3.8
Classifier: Programming Language :: Python :: 3.9
Requires-Python: >=3.6
Requires-Dist: pydot
